httpx_retry/__init__.py
httpx_retry/executor.py
httpx_retry/policies/__init__.py
httpx_retry/policies/base.py
httpx_retry/py.typed
httpx_retry/transports.py
httpx_retry-2025.4.23.dist-info/LICENSE
httpx_retry-2025.4.23.dist-info/METADATA
httpx_retry-2025.4.23.dist-info/WHEEL
httpx_retry-2025.4.23.dist-info/RECORD
