Metadata-Version: 2.1
Name: httpx-retry
Version: 2025.4.23
Summary: Middleware for implementing retry policies with HTTPX
Home-page: https://github.com/mharrisb1/httpx-retry
License: MIT
Keywords: httpx,retry
Author: Michael Harris
Author-email: mharris@definite.app
Requires-Python: >=3.9,<4.0
Classifier: License :: OSI Approved :: MIT License
Classifier: Programming Language :: Python :: 3
Classifier: Programming Language :: Python :: 3.9
Classifier: Programming Language :: Python :: 3.10
Classifier: Programming Language :: Python :: 3.11
Classifier: Programming Language :: Python :: 3.12
Requires-Dist: httpx (>=0.27.0,<1.0)
Project-URL: Documentation, https://github.com/mharrisb1/httpx-retry
Project-URL: Repository, https://github.com/mharrisb1/httpx-retry
